flask_travis.py
setup.py
Flask_Travis.egg-info/PKG-INFO
Flask_Travis.egg-info/SOURCES.txt
Flask_Travis.egg-info/dependency_links.txt
Flask_Travis.egg-info/not-zip-safe
Flask_Travis.egg-info/requires.txt
Flask_Travis.egg-info/top_level.txt