Metadata-Version: 1.1
Name: Flask-Travis
Version: 0.0.2
Summary: Easily fetch Travis CI environment variables when testing.
Home-page: https://github.com/cburmeister/flask-travis
Author: Corey Burmeister
Author-email: cburmeister@discogs.com
License: MIT
Platform: any
Classifier: Environment :: Web Environment
Classifier: Intended Audience :: Developers
Classifier: Programming Language :: Python
Classifier: Topic :: Internet :: WWW/HTTP :: Dynamic Content
Classifier: Topic :: Software Development :: Libraries :: Python Modules
